{
    "team": [
        {
            "name": "M.I.M. Imaadh",
            "email": "e22151@eng.pdn.ac.lk",
            "eNumber": "E/22/151"
        },
        {
            "name": "R. DAKSHAYANI",
            "email": "e22060@eng.pdn.ac.lk",
            "eNumber": "E/22/060"
        },
        {
            "name": "D.A. Victor",
            "email": "e22405@eng.pdn.ac.lk",
            "eNumber": "E/22/405"
        },
        {
            "name": "P.G.D.D. Chandrawansha",
            "email": "e22056@eng.pdn.ac.lk",
            "eNumber": "E/22/056"
        }
    ],
    "supervisors": [
        {
            "name": "Dr. Asitha Bandaranayake",
            "email": "asithab@eng.pdn.ac.lk"
        },
        {
            "name": "S. Ganathipan",
            "email": "e21148@eng.pdn.ac.lk"
        }
    ],
    "tags": ["Web", "Software Systems", "CO2060"],
    "image":"cover_page.jpg",
    "thumbnail":"thumbnail.jpg"
}
